odoo10_addon_storage_backend-10.0.1.0.1-py3.8-nspkg.pth
odoo/addons/storage_backend/README.rst
odoo/addons/storage_backend/__init__.py
odoo/addons/storage_backend/__manifest__.py
odoo/addons/storage_backend/components/__init__.py
odoo/addons/storage_backend/components/base_adapter.py
odoo/addons/storage_backend/components/filesystem_adapter.py
odoo/addons/storage_backend/data/data.xml
odoo/addons/storage_backend/i18n/storage_backend.pot
odoo/addons/storage_backend/models/__init__.py
odoo/addons/storage_backend/models/keychain.py
odoo/addons/storage_backend/models/storage_backend.py
odoo/addons/storage_backend/security/ir.model.access.csv
odoo/addons/storage_backend/static/description/icon.png
odoo/addons/storage_backend/tests/__init__.py
odoo/addons/storage_backend/tests/common.py
odoo/addons/storage_backend/tests/test_filesystem.py
odoo/addons/storage_backend/views/backend_storage_view.xml
odoo10_addon_storage_backend-10.0.1.0.1.dist-info/METADATA
odoo10_addon_storage_backend-10.0.1.0.1.dist-info/WHEEL
odoo10_addon_storage_backend-10.0.1.0.1.dist-info/namespace_packages.txt
odoo10_addon_storage_backend-10.0.1.0.1.dist-info/top_level.txt
odoo10_addon_storage_backend-10.0.1.0.1.dist-info/RECORD
